{
  "label": "base_greedy",
  "model": "gemma-4-e4b-it",
  "years": [
    "2024"
  ],
  "k": 1,
  "sampling": {
    "temperature": 0.0,
    "top_p": 1.0,
    "top_k": -1,
    "max_tokens": 3072,
    "seed": 1234,
    "enable_thinking": false
  },
  "max_num_seqs": 32,
  "created_at": "20260616T200717Z",
  "submission": "submissions/int4_base_aime",
  "serve_overrides": {
    "PRECACHE_BENCH": "0",
    "PRECACHE_REQUIRE": "0",
    "PRECACHE_DATASET": "/tmp/senpai_aime_no_precache.json",
    "MAX_NUM_SEQS": "32"
  },
  "n_problems": 30,
  "maj_k": 1,
  "maj_k_accuracy": 0.26666666666666666,
  "n_correct_maj": 8,
  "mean_pass_rate": 0.26666666666666666,
  "extract_fail_rate": 0.0,
  "total_samples": 30,
  "wall_s": 874.0919659137726,
  "per_problem": [
    {
      "id": "2024-II-4",
      "year": "2024",
      "gold": 33,
      "answers": [
        8
      ],
      "answer_counts": {
        "8": 1
      },
      "maj_answer": 8,
      "maj_correct": false,
      "correct_samples": 0,
      "k": 1,
      "pass_rate": 0.0,
      "finish_reasons": [
        "stop"
      ],
      "sample_chars": [
        3167
      ]
    },
    {
      "id": "2024-II-12",
      "year": "2024",
      "gold": 23,
      "answers": [
        4
      ],
      "answer_counts": {
        "4": 1
      },
      "maj_answer": 4,
      "maj_correct": false,
      "correct_samples": 0,
      "k": 1,
      "pass_rate": 0.0,
      "finish_reasons": [
        "length"
      ],
      "sample_chars": [
        7055
      ]
    },
    {
      "id": "2024-I-4",
      "year": "2024",
      "gold": 116,
      "answers": [
        116
      ],
      "answer_counts": {
        "116": 1
      },
      "maj_answer": 116,
      "maj_correct": true,
      "correct_samples": 1,
      "k": 1,
      "pass_rate": 1.0,
      "finish_reasons": [
        "stop"
      ],
      "sample_chars": [
        2634
      ]
    },
    {
      "id": "2024-I-3",
      "year": "2024",
      "gold": 809,
      "answers": [
        809
      ],
      "answer_counts": {
        "809": 1
      },
      "maj_answer": 809,
      "maj_correct": true,
      "correct_samples": 1,
      "k": 1,
      "pass_rate": 1.0,
      "finish_reasons": [
        "stop"
      ],
      "sample_chars": [
        7038
      ]
    },
    {
      "id": "2024-I-8",
      "year": "2024",
      "gold": 197,
      "answers": [
        272
      ],
      "answer_counts": {
        "272": 1
      },
      "maj_answer": 272,
      "maj_correct": false,
      "correct_samples": 0,
      "k": 1,
      "pass_rate": 0.0,
      "finish_reasons": [
        "length"
      ],
      "sample_chars": [
        10283
      ]
    },
    {
      "id": "2024-I-12",
      "year": "2024",
      "gold": 385,
      "answers": [
        2
      ],
      "answer_counts": {
        "2": 1
      },
      "maj_answer": 2,
      "maj_correct": false,
      "correct_samples": 0,
      "k": 1,
      "pass_rate": 0.0,
      "finish_reasons": [
        "length"
      ],
      "sample_chars": [
        6409
      ]
    },
    {
      "id": "2024-I-11",
      "year": "2024",
      "gold": 371,
      "answers": [
        4
      ],
      "answer_counts": {
        "4": 1
      },
      "maj_answer": 4,
      "maj_correct": false,
      "correct_samples": 0,
      "k": 1,
      "pass_rate": 0.0,
      "finish_reasons": [
        "length"
      ],
      "sample_chars": [
        7502
      ]
    },
    {
      "id": "2024-II-11",
      "year": "2024",
      "gold": 601,
      "answers": [
        3
      ],
      "answer_counts": {
        "3": 1
      },
      "maj_answer": 3,
      "maj_correct": false,
      "correct_samples": 0,
      "k": 1,
      "pass_rate": 0.0,
      "finish_reasons": [
        "length"
      ],
      "sample_chars": [
        5484
      ]
    },
    {
      "id": "2024-I-2",
      "year": "2024",
      "gold": 25,
      "answers": [
        25
      ],
      "answer_counts": {
        "25": 1
      },
      "maj_answer": 25,
      "maj_correct": true,
      "correct_samples": 1,
      "k": 1,
      "pass_rate": 1.0,
      "finish_reasons": [
        "stop"
      ],
      "sample_chars": [
        4213
      ]
    },
    {
      "id": "2024-II-6",
      "year": "2024",
      "gold": 55,
      "answers": [
        55
      ],
      "answer_counts": {
        "55": 1
      },
      "maj_answer": 55,
      "maj_correct": true,
      "correct_samples": 1,
      "k": 1,
      "pass_rate": 1.0,
      "finish_reasons": [
        "stop"
      ],
      "sample_chars": [
        4256
      ]
    },
    {
      "id": "2024-I-7",
      "year": "2024",
      "gold": 540,
      "answers": [
        540
      ],
      "answer_counts": {
        "540": 1
      },
      "maj_answer": 540,
      "maj_correct": true,
      "correct_samples": 1,
      "k": 1,
      "pass_rate": 1.0,
      "finish_reasons": [
        "stop"
      ],
      "sample_chars": [
        2953
      ]
    },
    {
      "id": "2024-II-3",
      "year": "2024",
      "gold": 45,
      "answers": [
        8
      ],
      "answer_counts": {
        "8": 1
      },
      "maj_answer": 8,
      "maj_correct": false,
      "correct_samples": 0,
      "k": 1,
      "pass_rate": 0.0,
      "finish_reasons": [
        "length"
      ],
      "sample_chars": [
        5942
      ]
    },
    {
      "id": "2024-I-1",
      "year": "2024",
      "gold": 204,
      "answers": [
        204
      ],
      "answer_counts": {
        "204": 1
      },
      "maj_answer": 204,
      "maj_correct": true,
      "correct_samples": 1,
      "k": 1,
      "pass_rate": 1.0,
      "finish_reasons": [
        "stop"
      ],
      "sample_chars": [
        3272
      ]
    },
    {
      "id": "2024-II-7",
      "year": "2024",
      "gold": 699,
      "answers": [
        0
      ],
      "answer_counts": {
        "0": 1
      },
      "maj_answer": 0,
      "maj_correct": false,
      "correct_samples": 0,
      "k": 1,
      "pass_rate": 0.0,
      "finish_reasons": [
        "length"
      ],
      "sample_chars": [
        6020
      ]
    },
    {
      "id": "2024-I-6",
      "year": "2024",
      "gold": 294,
      "answers": [
        294
      ],
      "answer_counts": {
        "294": 1
      },
      "maj_answer": 294,
      "maj_correct": true,
      "correct_samples": 1,
      "k": 1,
      "pass_rate": 1.0,
      "finish_reasons": [
        "stop"
      ],
      "sample_chars": [
        3970
      ]
    },
    {
      "id": "2024-I-13",
      "year": "2024",
      "gold": 110,
      "answers": [
        289
      ],
      "answer_counts": {
        "289": 1
      },
      "maj_answer": 289,
      "maj_correct": false,
      "correct_samples": 0,
      "k": 1,
      "pass_rate": 0.0,
      "finish_reasons": [
        "length"
      ],
      "sample_chars": [
        6363
      ]
    },
    {
      "id": "2024-I-15",
      "year": "2024",
      "gold": 721,
      "answers": [
        1
      ],
      "answer_counts": {
        "1": 1
      },
      "maj_answer": 1,
      "maj_correct": false,
      "correct_samples": 0,
      "k": 1,
      "pass_rate": 0.0,
      "finish_reasons": [
        "length"
      ],
      "sample_chars": [
        6899
      ]
    },
    {
      "id": "2024-II-15",
      "year": "2024",
      "gold": 315,
      "answers": [
        147
      ],
      "answer_counts": {
        "147": 1
      },
      "maj_answer": 147,
      "maj_correct": false,
      "correct_samples": 0,
      "k": 1,
      "pass_rate": 0.0,
      "finish_reasons": [
        "stop"
      ],
      "sample_chars": [
        8045
      ]
    },
    {
      "id": "2024-II-10",
      "year": "2024",
      "gold": 468,
      "answers": [
        52
      ],
      "answer_counts": {
        "52": 1
      },
      "maj_answer": 52,
      "maj_correct": false,
      "correct_samples": 0,
      "k": 1,
      "pass_rate": 0.0,
      "finish_reasons": [
        "length"
      ],
      "sample_chars": [
        7623
      ]
    },
    {
      "id": "2024-II-9",
      "year": "2024",
      "gold": 902,
      "answers": [
        2
      ],
      "answer_counts": {
        "2": 1
      },
      "maj_answer": 2,
      "maj_correct": false,
      "correct_samples": 0,
      "k": 1,
      "pass_rate": 0.0,
      "finish_reasons": [
        "length"
      ],
      "sample_chars": [
        8195
      ]
    },
    {
      "id": "2024-II-14",
      "year": "2024",
      "gold": 211,
      "answers": [
        12
      ],
      "answer_counts": {
        "12": 1
      },
      "maj_answer": 12,
      "maj_correct": false,
      "correct_samples": 0,
      "k": 1,
      "pass_rate": 0.0,
      "finish_reasons": [
        "length"
      ],
      "sample_chars": [
        6205
      ]
    },
    {
      "id": "2024-II-5",
      "year": "2024",
      "gold": 80,
      "answers": [
        370
      ],
      "answer_counts": {
        "370": 1
      },
      "maj_answer": 370,
      "maj_correct": false,
      "correct_samples": 0,
      "k": 1,
      "pass_rate": 0.0,
      "finish_reasons": [
        "stop"
      ],
      "sample_chars": [
        9592
      ]
    },
    {
      "id": "2024-I-9",
      "year": "2024",
      "gold": 480,
      "answers": [
        20
      ],
      "answer_counts": {
        "20": 1
      },
      "maj_answer": 20,
      "maj_correct": false,
      "correct_samples": 0,
      "k": 1,
      "pass_rate": 0.0,
      "finish_reasons": [
        "length"
      ],
      "sample_chars": [
        7338
      ]
    },
    {
      "id": "2024-II-2",
      "year": "2024",
      "gold": 236,
      "answers": [
        1
      ],
      "answer_counts": {
        "1": 1
      },
      "maj_answer": 1,
      "maj_correct": false,
      "correct_samples": 0,
      "k": 1,
      "pass_rate": 0.0,
      "finish_reasons": [
        "length"
      ],
      "sample_chars": [
        6701
      ]
    },
    {
      "id": "2024-II-1",
      "year": "2024",
      "gold": 73,
      "answers": [
        3
      ],
      "answer_counts": {
        "3": 1
      },
      "maj_answer": 3,
      "maj_correct": false,
      "correct_samples": 0,
      "k": 1,
      "pass_rate": 0.0,
      "finish_reasons": [
        "length"
      ],
      "sample_chars": [
        7193
      ]
    },
    {
      "id": "2024-I-10",
      "year": "2024",
      "gold": 113,
      "answers": [
        31
      ],
      "answer_counts": {
        "31": 1
      },
      "maj_answer": 31,
      "maj_correct": false,
      "correct_samples": 0,
      "k": 1,
      "pass_rate": 0.0,
      "finish_reasons": [
        "stop"
      ],
      "sample_chars": [
        9061
      ]
    },
    {
      "id": "2024-II-8",
      "year": "2024",
      "gold": 127,
      "answers": [
        2
      ],
      "answer_counts": {
        "2": 1
      },
      "maj_answer": 2,
      "maj_correct": false,
      "correct_samples": 0,
      "k": 1,
      "pass_rate": 0.0,
      "finish_reasons": [
        "length"
      ],
      "sample_chars": [
        9820
      ]
    },
    {
      "id": "2024-I-14",
      "year": "2024",
      "gold": 104,
      "answers": [
        30
      ],
      "answer_counts": {
        "30": 1
      },
      "maj_answer": 30,
      "maj_correct": false,
      "correct_samples": 0,
      "k": 1,
      "pass_rate": 0.0,
      "finish_reasons": [
        "length"
      ],
      "sample_chars": [
        6509
      ]
    },
    {
      "id": "2024-I-5",
      "year": "2024",
      "gold": 104,
      "answers": [
        2
      ],
      "answer_counts": {
        "2": 1
      },
      "maj_answer": 2,
      "maj_correct": false,
      "correct_samples": 0,
      "k": 1,
      "pass_rate": 0.0,
      "finish_reasons": [
        "length"
      ],
      "sample_chars": [
        7106
      ]
    },
    {
      "id": "2024-II-13",
      "year": "2024",
      "gold": 321,
      "answers": [
        321
      ],
      "answer_counts": {
        "321": 1
      },
      "maj_answer": 321,
      "maj_correct": true,
      "correct_samples": 1,
      "k": 1,
      "pass_rate": 1.0,
      "finish_reasons": [
        "stop"
      ],
      "sample_chars": [
        5593
      ]
    }
  ]
}