{
  "control_file": "research/validity/bi_detax_surgical_attn/surgattn_overhead_785/control/decode_outputs.jsonl",
  "variant_file": "research/validity/bi_detax_surgical_attn/surgattn_overhead_785/variant/decode_outputs.jsonl",
  "n_records_control": 32,
  "n_records_variant": 32,
  "n_common": 32,
  "only_in_control": [],
  "only_in_variant": [],
  "identical_records": 30,
  "diverging_records": 2,
  "record_divergence_rate": 0.0625,
  "total_tokens_compared": 16384,
  "total_token_diffs": 289,
  "token_divergence_rate": 0.01763916015625,
  "byte_exact_greedy_identity": false,
  "diverging_detail": [
    {
      "id": "mmlu_pro-001de7fe6d",
      "first_divergence_pos": 267,
      "len_control": 512,
      "len_variant": 512,
      "n_token_diffs": 240
    },
    {
      "id": "mmlu_pro-006f3a2112",
      "first_divergence_pos": 463,
      "len_control": 512,
      "len_variant": 512,
      "n_token_diffs": 49
    }
  ]
}