{
  "created_at": "20260615T052146Z",
  "pr": 295,
  "agent": "wirbel",
  "kind": "eagle3-step-profile",
  "synthesis": {
    "constants": {
      "official_baseline": 481.53,
      "target_tps": 500.0,
      "K_cal": 125.268,
      "step_us": 1218.2,
      "new_step_us": 1202.7171244939168,
      "tau": 1.218,
      "E_T_deployed": 3.844,
      "K_spec": 7,
      "E_T_max": 8.0,
      "linear_cap": 3.8445,
      "fern_floor_public": 4.966,
      "step_banked_target_290": 4.9029,
      "corrected_target_mfuse3_293": 6.1245,
      "corrected_target_band_293": [
        5.8017,
        6.1245
      ],
      "draft_k7_chain_us_278": 706.8555014474051,
      "bridge_draft": 0.2147122962556323,
      "linear_draft_norm_293": 149.84,
      "g_draft_frac_floor_283": 0.09167,
      "eagle3_target_layers": [
        2,
        21,
        39
      ],
      "L_fuse_deployed": 3,
      "draft_vocab_serve": 12288,
      "lin_geom": {
        "hid": 256,
        "heads": 4,
        "kv": 2,
        "head_dim": 256,
        "inter": 2048,
        "layers": 4
      },
      "eag_geom": {
        "hid": 2560,
        "heads": 8,
        "kv": 2,
        "head_dim": 256,
        "inter": 10240,
        "layers": 1,
        "fc_in": 7680
      }
    },
    "reproduce_293": {
      "repro_mfuse1": 4.9028839601352745,
      "resid_mfuse1": 1.60398647253146e-05,
      "repro_mfuse3": 6.124543096371696,
      "resid_mfuse3": 4.309637169530589e-05,
      "band_lo": 5.801766530035495,
      "band_hi": 6.124543096371696,
      "band_reproduced": true
    },
    "gpu_profile": {
      "gpu_available": true,
      "gpu_name": "NVIDIA A10G",
      "ctx": 528,
      "k_spec": 7,
      "vocab_head": 12288,
      "dtype": "bfloat16",
      "regime": "cuda-graph",
      "smoke": false,
      "smoke_nan_clean": true,
      "smoke_shapes": {
        "linear": [
          1,
          1,
          12288
        ],
        "eagle256": [
          1,
          1,
          12288
        ],
        "faithful": [
          1,
          1,
          12288
        ]
      },
      "graph_captured": {
        "linear": true,
        "eagle256": true,
        "faithful": true
      },
      "linear_chain_wall_us": 3000.831985473633,
      "eagle256_chain_wall_us": 3025.126361846924,
      "faithful_chain_wall_us": 5235.481643676758,
      "linear_chain_wall_us_all": [
        2999.398422241211,
        3000.115203857422,
        3001.4463424682617,
        3000.4735946655273,
        3001.3439178466797,
        3002.4703979492188,
        3000.320053100586,
        3001.241683959961,
        3001.139259338379,
        3001.3439178466797,
        3002.4192810058594,
        3002.3679733276367,
        3000.729560852051,
        2999.398422241211,
        3000.934410095215,
        2999.295997619629,
        2998.1184005737305,
        2999.091148376465,
        2998.8351821899414,
        3001.036834716797
      ],
      "eagle256_chain_wall_us_all": [
        3025.6128311157227,
        3024.742317199707,
        3023.923110961914,
        3025.4079818725586,
        3025.3055572509766,
        3024.947166442871,
        3024.3839263916016,
        3024.947166442871,
        3024.281692504883,
        3024.844741821289,
        3024.8960494995117,
        3025.3055572509766,
        3025.5104064941406,
        3024.7936248779297,
        3025.356864929199,
        3025.971221923828,
        3030.988883972168,
        3025.9199142456055,
        3024.742317199707,
        3025.356864929199
      ],
      "faithful_chain_wall_us_all": [
        5236.172866821289,
        5236.275100708008,
        5236.684799194336,
        5236.479949951172,
        5234.22737121582,
        5230.950546264648,
        5234.636688232422,
        5235.404968261719,
        5236.019134521484,
        5235.968017578125,
        5236.326217651367,
        5234.944152832031,
        5235.558319091797,
        5235.302352905273,
        5233.459091186523,
        5234.841537475586,
        5235.148620605469,
        5234.380722045898,
        5236.940765380859,
        5235.81428527832
      ],
      "linear_chain_wall_us_k1": 429.6192169189453,
      "eagle256_chain_wall_us_k1": 454.6048164367676,
      "faithful_chain_wall_us_k1": 841.0623550415039,
      "linear_per_step_us": 428.53546142578125,
      "eagle256_per_step_us": 428.4202575683594,
      "faithful_per_step_us": 732.4032147725424,
      "linear_fixed_us": 1.0837554931640625,
      "faithful_fixed_us": 108.65914026896155,
      "multiplier_256style": 1.008095880239512,
      "multiplier_faithful": 1.744676699335575,
      "per_step_multiplier_faithful": 1.709084266528987,
      "wall_delta_additive_us": 2234.649658203125,
      "peak_mem_gib": 1.906
    },
    "parametric": {
      "lin_step_bytes": 29491200,
      "eag_step_bytes": 263225344,
      "lin_chain_bytes": 206438400,
      "eag_chain_bytes": 1881899008,
      "e256_chain_bytes": 245760000,
      "parametric_multiplier_faithful": 9.116031746031746,
      "parametric_multiplier_256style": 1.1904761904761905,
      "head_bytes_lin": 6291456,
      "head_bytes_eag": 62914560,
      "fc_bytes": 39321600
    },
    "overhead_is_parametric": false,
    "measured_multiplier_faithful": 1.744676699335575,
    "measured_multiplier_256style": 1.008095880239512,
    "eagle3_draft_wall_us": 1233.2343231724515,
    "collapse_faithful": {
      "multiplier_vs_linear": 1.744676699335575,
      "eagle3_draft_wall_us": 1233.2343231724515,
      "wall_delta_us": 526.3788217250464,
      "eagle3_draft_norm_us": 113.0200055129188,
      "eagle3_step_measured_us": 1315.7371300068355,
      "eagle3_corrected_target_measured": 5.363610726985671,
      "measured_target_below_conservative": true,
      "measured_multiplier_vs_mfuse3": 0.5815588997785249,
      "measured_target_within_window": true,
      "measured_target_eats_free_lever": true,
      "headroom_eroded_pct": 36.55662921394949,
      "implied_eagle3_draft_frac": 0.19978155173864645,
      "tps_roundtrip": 500.00000000000006
    },
    "collapse_256style": {
      "multiplier_vs_linear": 1.008095880239512,
      "eagle3_draft_wall_us": 712.5781189337634,
      "wall_delta_us": 5.722617486358329,
      "eagle3_draft_norm_us": 1.2287163410886313,
      "eagle3_step_measured_us": 1203.9458408350054,
      "eagle3_corrected_target_measured": 4.907892830066193,
      "measured_target_below_conservative": true,
      "measured_multiplier_vs_mfuse3": 0.3360319600798373,
      "measured_target_within_window": true,
      "measured_target_eats_free_lever": false,
      "headroom_eroded_pct": 25.59000914610018,
      "implied_eagle3_draft_frac": 0.12547800010365404,
      "tps_roundtrip": 499.9999999999999
    },
    "collapse_additive": {
      "multiplier_vs_linear": 4.161395297380165,
      "eagle3_draft_wall_us": 2941.50515965053,
      "wall_delta_us": 2234.649658203125,
      "eagle3_draft_norm_us": 479.8067594396568,
      "eagle3_step_measured_us": 1682.5238839335736,
      "eagle3_corrected_target_measured": 6.858819247754167,
      "measured_target_below_conservative": false,
      "measured_multiplier_vs_mfuse3": 1.3871317657933881,
      "measured_target_within_window": true,
      "measured_target_eats_free_lever": true,
      "headroom_eroded_pct": 72.53806395750613,
      "implied_eagle3_draft_frac": 0.3742275313011339,
      "tps_roundtrip": 500.0
    },
    "collapse_at_mfuse3_check": {
      "multiplier_vs_linear": 3.0,
      "eagle3_draft_wall_us": 2120.5665043422155,
      "wall_delta_us": 1413.7110028948102,
      "eagle3_draft_norm_us": 303.54113567339755,
      "eagle3_step_measured_us": 1506.2582601673143,
      "eagle3_corrected_target_measured": 6.140271318331048,
      "measured_target_below_conservative": false,
      "measured_multiplier_vs_mfuse3": 1.0,
      "measured_target_within_window": true,
      "measured_target_eats_free_lever": true,
      "headroom_eroded_pct": 55.2465724541222,
      "implied_eagle3_draft_frac": 0.3009982734455088,
      "tps_roundtrip": 500.0
    },
    "step_decomposition": {
      "available": true,
      "linear_per_step_us": 428.53546142578125,
      "faithful_per_step_us": 732.4032147725424,
      "per_step_multiplier": 1.709084266528987,
      "faithful_fixed_us": 108.65914026896155,
      "achieved_gbps_linear": 68.81857548469797,
      "achieved_gbps_faithful": 359.3994929169558,
      "bw_util_pct_linear": 11.469762580782996,
      "bw_util_pct_faithful": 59.89991548615931,
      "bw_util_ratio": 5.222419824671747,
      "byte_ratio_x_bwfrac": 1.745557050577551,
      "linear_dispatch_bound": true
    },
    "regime_bracket": {
      "corrected_multiplicative_lower": 5.363610726985671,
      "corrected_additive_upper": 6.858819247754167,
      "corrected_central": 6.1112149873699195,
      "corrected_byte_budget_pure_bw": 9.924221500762902,
      "bracket_lo": 5.363610726985671,
      "bracket_hi": 6.858819247754167,
      "straddles_293": true,
      "within_window": true,
      "central_validates_293": true,
      "conservative_293": 6.1245
    },
    "eagle3_corrected_target_measured": 5.363610726985671,
    "measured_target_below_conservative": true,
    "self_test": {
      "conditions": {
        "a_basis_reproduces_293": true,
        "b_bridge_normalized_frac_bounded": true,
        "c_corrected_target_roundtrips_500": true,
        "d_gpu_smoke_nan_clean": true,
        "e_constants_exact": true,
        "f_caveats_present": true,
        "g_bracket_straddles_or_validates_293": true,
        "h_lower_bound_direction_proven": true
      },
      "passes": true
    },
    "handoff": "Profiled random-init on the A10G, the FAITHFUL EAGLE-3 fusion draft step (2560-dim, the repo's real Eagle3DraftHead) is 1.74x the deployed linear K=7 chain in the bf16 standalone-graph harness -- but that ratio is a dispatch-compressed LOWER bound: the tiny 256-dim linear runs at ~11% of A10G BW (dispatch-bound) vs the faithful's ~60% (near-bandwidth), so the deployed ONEGRAPH+INT4 regime that removes that overhead RAISES the true ratio. The two anchorings of the same measured pair bracket the corrected BUILT-raise target at [5.3636 mult-lower .. 6.8588 add-upper] (central 6.1112), which STRADDLES #293's conservative 6.1245 -- the measurement VALIDATES #293's proxy (its ASSUMED 3x ~ the regime-corrected ~3x measured) rather than collapsing it. All physical anchorings stay inside the 8.0 window; the pure-BW byte-budget extreme (9.92) is unphysical (deployed is not pure-BW). Size the kanna #294 Phase-1 gate against ~6.12; this leg bounds the step-cost DENOMINATOR, not the achieved E[T].",
    "caveats": [
      "0 TPS: this MEASURES the EAGLE-3 draft-step overhead (denominator); it is a random-init ARCHITECTURAL cost profile, NOT a trained build. It bounds the STEP COST, NOT the achieved E[T] -- the build's sufficiency (can it DELIVER the corrected target?) is the separate per-position acceptance question (kanna #289/#294 lane).",
      "The bridge 0.2147 is LOAD-BEARING: the measured WALL overhead is normalized through it (eagle3_draft_norm_us = 0.2147 x wall_delta). A full-wall attribution over-states the step inflation ~4.66x (the fern #287 error class).",
      "The multiplier is a RATIO of two random-init bf16 drafters timed in the SAME standalone CUDA-graph harness, anchored to the banked 706.86us linear wall. The raw measured ratio is a dispatch-compressed LOWER bound: the 256-dim linear runs at ~12% of A10G BW (tiny GEMMs, dispatch-bound) while the faithful runs near-bandwidth, so the harness ratio (byte-budget DEFLATED by the linear's worse BW utilization) under-states the overhead-free ratio. TWO regime corrections push in OPPOSITE directions and partly cancel: removing the standalone dispatch overhead (deployed ONEGRAPH) RAISES the ratio; INT4 weight-lightening (deployed body is INT4, the wider EAGLE-3 is more weight-bound) LOWERS it. The reported bracket [multiplicative lower, additive upper] spans the residual regime uncertainty; the parametric byte-budget is the PURE-BW (overhead-free, bf16) pessimistic extreme.",
      "ARCHITECTURE: the headline FAITHFUL multiplier uses the repo's real EAGLE-3 (train_eagle3.py / arch_notes.md: 2560-dim body). #293's 'm_fuse x linear' and this PR's 'sized like the deployed MTP drafter' BOTH implicitly priced a ~linear-width body; the faithful body is ~10x wider per layer (1 layer vs 4). The 256-style number is the advisor-literal lower bound, reported for completeness.",
      "The launch gate is UNCHANGED and human-approval-gated: land #245's MEASURED >=500 at lambda_hat>=0.9780 AND PPL<=2.42. This leg sizes the denominator only."
    ]
  },
  "eagle3_step_profile_self_test_passes": true,
  "eagle3_corrected_target_measured": 5.363610726985671,
  "measured_target_below_conservative": true,
  "eagle3_draft_wall_us": 1233.2343231724515,
  "peak_mem_mib": 5104.305,
  "nan_clean": true
}